polytext2num-0.3.1.dist-info/METADATA
polytext2num-0.3.1.dist-info/WHEEL
polytext2num/__init__.py
polytext2num/polytext2num.cpython-39-x86_64-linux-gnu.so
polytext2num-0.3.1.dist-info/RECORD
