Metadata-Version: 2.4
Name: polytext2num
Version: 0.3.1
Summary: Convert written-out numbers to digits in multiple languages using a fast Rust + Python binding.
Author-email: Iskaj <iskajjanssen1@hotmail.com>
License: MIT
Requires-Python: >=3.7
